juxtapose/__init__.py
juxtapose/conf/gd-ogc.py
juxtapose/data/__init__.py
juxtapose/data/build.py
juxtapose/data/loaders.py
juxtapose/data/utils.py
juxtapose/detectors/__init__.py
juxtapose/detectors/groundingdino/__init__.py
juxtapose/detectors/groundingdino/datasets/__init__.py
juxtapose/detectors/groundingdino/datasets/cocogrounding_eval.py
juxtapose/detectors/groundingdino/datasets/transforms.py
juxtapose/detectors/groundingdino/models/GroundingDINO/__init__.py
juxtapose/detectors/groundingdino/models/GroundingDINO/backbone/__init__.py
juxtapose/detectors/groundingdino/models/GroundingDINO/backbone/backbone.py
juxtapose/detectors/groundingdino/models/GroundingDINO/backbone/position_encoding.py
juxtapose/detectors/groundingdino/models/GroundingDINO/backbone/swin_transformer.py
juxtapose/detectors/groundingdino/models/GroundingDINO/bertwarper.py
juxtapose/detectors/groundingdino/models/GroundingDINO/csrc/MsDeformAttn/ms_deform_attn.h
juxtapose/detectors/groundingdino/models/GroundingDINO/csrc/MsDeformAttn/ms_deform_attn_cpu.cpp
juxtapose/detectors/groundingdino/models/GroundingDINO/csrc/MsDeformAttn/ms_deform_attn_cpu.h
juxtapose/detectors/groundingdino/models/GroundingDINO/csrc/MsDeformAttn/ms_deform_attn_cuda.cu
juxtapose/detectors/groundingdino/models/GroundingDINO/csrc/MsDeformAttn/ms_deform_attn_cuda.h
juxtapose/detectors/groundingdino/models/GroundingDINO/csrc/MsDeformAttn/ms_deform_im2col_cuda.cuh
juxtapose/detectors/groundingdino/models/GroundingDINO/csrc/cuda_version.cu
juxtapose/detectors/groundingdino/models/GroundingDINO/csrc/vision.cpp
juxtapose/detectors/groundingdino/models/GroundingDINO/fuse_modules.py
juxtapose/detectors/groundingdino/models/GroundingDINO/groundingdino.py
juxtapose/detectors/groundingdino/models/GroundingDINO/groundingdinoOld.py
juxtapose/detectors/groundingdino/models/GroundingDINO/ms_deform_attn.py
juxtapose/detectors/groundingdino/models/GroundingDINO/transformer.py
juxtapose-0.0.35.dist-info/LICENSE
juxtapose-0.0.35.dist-info/METADATA
juxtapose-0.0.35.dist-info/WHEEL
juxtapose-0.0.35.dist-info/RECORD
