Metadata-Version: 2.1
Name: juxtapose
Version: 0.0.35
Summary: 
License: MIT
Keywords: pose estimation,pose tracking,computer vision,deep learning,machine learning
Author: Zi Qin
Author-email: ziqinyeow@gmail.com
Requires-Python: >=3.8,<4.0
Classifier: Development Status :: 2 - Pre-Alpha
Classifier: Intended Audience :: Developers
Classifier: Intended Audience :: Education
Classifier: Intended Audience :: Science/Research
Classifier: License :: OSI Approved :: MIT License
Classifier: Operating System :: MacOS
Classifier: Operating System :: Microsoft :: Windows
Classifier: Operating System :: POSIX :: Linux
Classifier: Programming Language :: Python :: 3
Classifier: Programming Language :: Python :: 3.8
Classifier: Programming Language :: Python :: 3.9
Classifier: Programming Language :: Python :: 3.10
Classifier: Programming Language :: Python :: 3.11
Classifier: Programming Language :: Python :: 3.12
Classifier: Topic :: Scientific/Engineering
Classifier: Topic :: Scientific/Engineering :: Artificial Intelligence
Classifier: Topic :: Scientific/Engineering :: Image Recognition
Classifier: Topic :: Software Development
Requires-Dist: addict
Requires-Dist: aenum (==3.1.15)
Requires-Dist: chex
Requires-Dist: dm-haiku
Requires-Dist: dm-tree
Requires-Dist: einshape
Requires-Dist: ipympl
Requires-Dist: jax (==0.4.24)
Requires-Dist: jaxlib (==0.4.23)
Requires-Dist: jaxline
Requires-Dist: lapx (==0.5.2)
Requires-Dist: mediapy
Requires-Dist: onnx (==1.16.0)
Requires-Dist: onnxruntime (==1.17.1) ; sys_platform == "darwin"
Requires-Dist: onnxruntime (==1.17.1) ; sys_platform == "linux"
Requires-Dist: onnxruntime-gpu (==1.17.1) ; sys_platform == "win32"
Requires-Dist: opencv-contrib-python
Requires-Dist: opencv-python
Requires-Dist: optax
Requires-Dist: packaging (==23.1)
Requires-Dist: pycocotools
Requires-Dist: supervision (==0.17.1)
Requires-Dist: timm
Requires-Dist: tqdm (>=4.65.0,<5.0.0)
Requires-Dist: transformers
Requires-Dist: typing_extensions
Requires-Dist: yapf
Project-URL: Bug Tracker, https://github.com/ziqinyeow/juxtapose/issues
Project-URL: Documentation, https://sdk.juxt.space
Project-URL: Homepage, https://juxt.space
Project-URL: Source Code, https://github.com/ziqinyeow/juxtapose
